synerex_harmovis/__init__.py
synerex_harmovis/sxharmovis.py
synerex_harmovis/examples/__init__.py
synerex_harmovis/examples/graphdemo.py
synerex_harmovis/proto/__init__.py
synerex_harmovis/proto/api.py
synerex_harmovis/proto/geography.py
synerex_harmovis/proto/nodeapi.py
synerex_harmovis-0.5.3.dist-info/LICENSE
synerex_harmovis-0.5.3.dist-info/METADATA
synerex_harmovis-0.5.3.dist-info/WHEEL
synerex_harmovis-0.5.3.dist-info/top_level.txt
synerex_harmovis-0.5.3.dist-info/RECORD
