Metadata-Version: 2.1
Name: synerex-harmovis
Version: 0.5.3
Summary: Python library for Synerex and HarmoViS
Home-page: https://github.com/synerex/python_Synerex-HarmoVIS
Author: Nobuo Kawaguchi
Author-email: kawaguti@synerex.net
License: UNKNOWN
Project-URL: Bug Reports, https://github.com/synerex/python_Synerex-HarmoVIS/issues
Project-URL: Source, https://github.com/synerex/python_Synerex-HarmoVIS/
Keywords: visualization synerex harmoware-vis
Platform: UNKNOWN
Classifier: Development Status :: 3 - Alpha
Classifier: Intended Audience :: Developers
Classifier: Topic :: Scientific/Engineering :: Visualization
Classifier: License :: OSI Approved :: Apache Software License
Classifier: Programming Language :: Python :: 3
Classifier: Programming Language :: Python :: 3.7
Classifier: Programming Language :: Python :: 3.8
Classifier: Programming Language :: Python :: 3 :: Only
Requires-Python: >=3.7, <4
Requires-Dist: betterproto
Requires-Dist: grpclib
